misclib/__init__.py
misclib/__main__.py
misclib/constants.py
misclib/utils/path.py
misclib/utils/string.py
misclib-0.1.2.dist-info/METADATA
misclib-0.1.2.dist-info/WHEEL
misclib-0.1.2.dist-info/entry_points.txt
misclib-0.1.2.dist-info/licenses/LICENSE.txt
misclib-0.1.2.dist-info/RECORD
